[
  {
    "type": "put",
    "key": "project~1",
    "value": {
      "id": 1,
      "title": "Sample Project",
      "description": "This is a description of the initial sample project",
      "manager": "Tony Bradley",
      "start": "2015/9/26 9:00",
      "projectedStart": "2015/9/26 9:00",
      "end": "2015/9/27 9:00",
      "projectedEnd": "2015/9/27 9:00"
    }
  },
  {
    "type": "put",
    "key": "project~2",
    "value": {
      "id": 2,
      "title": "Other Project",
      "description": "This is a description of the other project",
      "manager": "Zod",
      "start": "2015/9/26 9:00",
      "projectedStart": "2015/9/26 9:00",
      "end": "2015/9/27 9:00",
      "projectedEnd": "2015/9/27 9:00"
    }
  },
  {
    "type": "put",
    "key": "project~3",
    "value": {
      "id": 3,
      "title": "Final Project",
      "description": "This is a description of the final project",
      "manager": "Supes",
      "start": "2015/9/26 9:00",
      "projectedStart": "2015/9/26 9:00",
      "end": "2015/9/27 9:00",
      "projectedEnd": "2015/9/27 9:00"
    }
  },
  {
    "type": "put",
    "key": "projectTeam~1",
    "value": [
      {
        "id": 1,
        "name": "Tony Bradley",
        "email": "antbradley91@gmail.com",
        "phone": "555-5555",
        "position": "Code Monkey"
      }
    ]
  },
  {
    "type": "put",
    "key": "projectTeam~2",
    "value": [
      {
        "id": 1,
        "name": "Tony Bradley",
        "email": "antbradley91@gmail.com",
        "phone": "555-5555",
        "position": "Code Monkey"
      }
    ]
  },
  {
    "type": "put",
    "key": "projectTeam~3",
    "value": [
      {
        "id": 1,
        "name": "Tony Bradley",
        "email": "antbradley91@gmail.com",
        "phone": "555-5555",
        "position": "Code Monkey"
      }
    ]  
  },
  {
    "type": "put",
    "key": "task~1~1",
    "value": {
      "id": 1,
      "title": "Sample Project Task One",
      "description": "This is a description of sample project task one",
      "start": "2015/9/26 9:00",
      "end": "2015/9/26 11:00"
    }
  },
  {
    "type": "put",
    "key": "task~1~2",
    "value": {
      "id": 2,
      "title": "Sample Project Task Two",
      "description": "This is a description of sample project task two",
      "start": "2015/9/26 8:00",
      "end": "2015/9/26 9:00"
    }
  },
  {
    "type": "put",
    "key": "task~1~3",
    "value": {
      "id": 3,
      "title": "Sample Project Task Three",
      "description": "This is a description of sample project task three",
      "start": "2015/9/26 11:00",
      "end": "2015/9/26 12:00"
    }
  },
  {
    "type": "put",
    "key": "task~2~1",
    "value": {
      "id": 1,
      "title": "Other Project Task Three",
      "description": "This is a description of other project task one",
      "start": "2015/9/26 11:00",
      "end": "2015/9/26 12:00"
    }
  },
  {
    "type": "put",
    "key": "dependency~1~1~1",
    "value": {
      "id": 1,
      "predecessorId": 1,
      "successorId": 2,
      "type": 0
    }
  },
  {
    "type": "put",
    "key": "teamMember~1",
    "value": {
      "id": 1,
      "name": "Tony Bradley",
      "email": "antbradley91@gmail.com",
      "phone": "555-5555",
      "position": "Code Monkey"
    }
  }
]
